{
  "defaultInitialization": false,
  "filePreviewOnHover": false,
  "flowMenuEnabled": true,
  "markSans": false,
  "blinkEnabled": false,
  "makeMenuPlaceholder": true,
  "mobileMakeBar": true,
  "inlineStyler": true,
  "makerMode": true,
  "inlineStylerColors": false,
  "editorFlow": true,
  "internalLinkClickFlow": true,
  "contextEnabled": true,
  "saveAllContextToFrontmatter": true,
  "editorFlowStyle": "seamless",
  "autoOpenFileContext": false,
  "activeView": "root",
  "hideFrontmatter": true,
  "activeSpace": "",
  "spacesCompactMode": true,
  "defaultDateFormat": "yyyy-MM-dd",
  "spacesEnabled": true,
  "spacesPerformance": false,
  "collapsedTags": [],
  "enableFolderNote": true,
  "folderIndentationLines": true,
  "revealActiveFile": false,
  "spacesStickers": true,
  "spaceRowHeight": 29,
  "spacesDisablePatch": false,
  "folderNoteInsideFolder": false,
  "folderNoteDefaultView": false,
  "sidebarTabs": true,
  "showRibbon": true,
  "deleteFileOption": "system-trash",
  "expandedFolders": {
    "Obsidian": [
      "Private",
      "Private/Protected",
      "Public",
      "C++/STL/Container",
      "C++/Modern C++/Library",
      "C++/C++ Code Keeping",
      "C++/C++ Code Keeping",
      "C++/C++ Code Keeping",
      "Math",
      "Math",
      "Math",
      "C++/STL/Container/시퀀스 컨테이너",
      "Excalidraw",
      "수학적 지식/contents",
      "Computer Science",
      "Computer Science/프로그래밍 규범",
      "프로그래밍 규범",
      "Computer Science",
      "프로그래밍 규범",
      "프로그래밍 규범",
      "프로그래밍 용어 및 규범",
      "C++/STL/Container/연관 컨테이너",
      "C++/STL/Container",
      "C++/STL/Container",
      "C++/STL/Container/해시 컨테이너",
      "C++/STL/Container",
      "C++/STL/Container",
      "C++/STL/Container/컨테이너 어댑터",
      "C++/STL/Iteraoter",
      "C++/STL/Container/시퀀스 컨테이너",
      "C++/STL/Algorithm",
      "자료구조/선형구조",
      "자료구조/비선형 구조",
      "/",
      "알고리즘",
      "contents",
      "contents",
      "CS 지식/Git",
      "자료구조",
      "C++/C++ STL/Container",
      "C++/C++ STL/Container/컨테이너 어댑터",
      "CS 지식/자료구조/심화 자료구조",
      "C++/C++ STL/Container/시퀀스 컨테이너",
      "C++/C++ STL/Container/연관 컨테이너",
      "C++/C++ STL/Container/해시 컨테이너",
      "C++/C++ STL/Iteraoter",
      "C++/C++ STL/Algorithm",
      "C++/C++ STL/Container/해시 컨테이너",
      "CS 지식/디자인패턴/생성패턴",
      "CS 지식/디자인패턴/구조패턴",
      "C++/contents",
      "C++/개념정리/contents",
      "CS 지식/디자인패턴/구조패턴",
      "일기장/공부",
      "일기장/프로젝트",
      "일기장/프로젝트/contents",
      "CS 지식",
      "CS 지식/디자인패턴",
      "CS 지식/디자인패턴/행동패턴",
      "CS 지식/디자인패턴/구조패턴",
      "CS 지식/디자인패턴/구조패턴",
      "CS 지식/디자인패턴/구조패턴"
    ],
    "as": [
      "Hello Obsidian",
      "Hello Obsidian",
      "Protected",
      "Obsidian_Public",
      "Obsidian_Public/Public",
      "Obsidian_Public",
      "Obsidian_Public/Public",
      "Obsidian_Private",
      "Obsidian_Private",
      "Obsidian_Private/Private",
      "Obsidian_Private/Protected",
      "Obsidian_Private/Personal",
      "Obsidian_Private/Protected",
      "Obsidian_Private/Private",
      "Obsidian_Private/Personal",
      "Obsidian_Private/Protected",
      "Obsidian_Private/Protected",
      "Obsidian_Private/Protected",
      "Obsidian_Private/Private",
      "Obsidian_Private/Personal",
      "Obsidian_Private/Private",
      "Obsidian_Private/Protected",
      "Obsidian_Public/Hello Obsidian",
      "Obsidian_Public/Hello Obsidian",
      "Obsidian_Private/Protected"
    ],
    "test": [
      "Hello Obsidian",
      "Private",
      "Private/Private",
      "Private/Personal",
      "Private/Protected",
      "Public"
    ],
    "priv": [
      "Private/Personal",
      "Private/Protected",
      "Private/Private",
      "Private/Private"
    ],
    "Public": [
      "Hello Obsidian",
      "Notepad",
      "C++",
      "C++",
      "C++/STL/Container/시퀀스 컨테이너",
      "C++/STL/Container/연관 컨테이너",
      "C++/STL/Container/연관 컨테이너",
      "C++/STL/Container/연관 컨테이너",
      "C++/Modern C++",
      "C++/Modern C++/Library",
      "C++/Modern C++/Library",
      "C++/STL"
    ]
  },
  "expandedSpaces": [
    "/",
    null,
    "Obsidian",
    "testSpace1",
    "as",
    "test",
    "priv",
    "Hello Obsidian",
    "Private",
    "another_private",
    null
  ],
  "expandFolderOnClick": true,
  "openFolders": [],
  "fileIcons": [],
  "cachedSpaces": [
    "Obsidian"
  ],
  "menuTriggerChar": "/",
  "inlineStickerMenu": false,
  "emojiTriggerChar": ":",
  "folderContextFile": "context",
  "tagContextFolder": "Context",
  "hiddenFiles": [
    "Context"
  ],
  "lineNumbers": false,
  "hiddenExtensions": [
    ".mdb"
  ],
  "inlineBacklinks": false,
  "inlineContext": false,
  "inlineBacklinksExpanded": false,
  "inlineContextExpanded": true,
  "inlineContextSectionsExpanded": false,
  "dataviewInlineContext": false,
  "inlineContextNameLayout": "vertical",
  "spacesSyncLastUpdated": "Context/spacesLastSync.log",
  "spacesSyncTimeoutSeconds": 10,
  "spacesAutoBackup": true,
  "spacesAutoBackupInterval": 10,
  "spacesAutoBackupLast": 1714678012136,
  "spacesUseAlias": false,
  "precreateVaultSpace": true,
  "fmKeyAlias": "aliases",
  "fmKeyBanner": "banner",
  "fmKeyColor": "color",
  "fmKeySticker": "sticker",
  "openSpacesOnLaunch": true,
  "indexSVG": false,
  "readableLineWidth": true
}